dedllogin/__init__.py
dedllogin/dedl_login.py
dedllogin-0.4.dist-info/METADATA
dedllogin-0.4.dist-info/WHEEL
dedllogin-0.4.dist-info/top_level.txt
dedllogin-0.4.dist-info/RECORD
