Metadata-Version: 2.1
Name: dedllogin
Version: 0.4
Requires-Dist: requests
